click/plus/__init__.py
click/plus/api.py
click/plus/base.py
click/plus/goodies/__init__.py
click/plus/goodies/logger.py
click/plus/goodies/report.py
click_plus-0.0.3.dist-info/LICENSE
click_plus-0.0.3.dist-info/METADATA
click_plus-0.0.3.dist-info/WHEEL
click_plus-0.0.3.dist-info/top_level.txt
click_plus-0.0.3.dist-info/RECORD
